empty_decorator/__init__.py
empty_decorator/empty_decorator.py
empty_decorator/version.py
empty_decorator-1.0.0rc1.dist-info/METADATA
empty_decorator-1.0.0rc1.dist-info/WHEEL
empty_decorator-1.0.0rc1.dist-info/licenses/LICENSE
empty_decorator-1.0.0rc1.dist-info/RECORD
