Metadata-Version: 2.3
Name: empty-decorator
Version: 1.0.0rc1
Summary: The project contains empty decorator
Project-URL: Homepage, https://github.com/alexstaf/empty-decorator
Project-URL: Issues, https://github.com/alexstaf/empty-decorator/issues
Author: alexstaf
Classifier: License :: OSI Approved :: MIT License
Classifier: Operating System :: OS Independent
Classifier: Programming Language :: Python :: 3
Requires-Python: >=3.8
